dir_handeler/__init__.py
dir_handeler/dir.py
dir_handeler-0.0.1.dist-info/LICENSE
dir_handeler-0.0.1.dist-info/METADATA
dir_handeler-0.0.1.dist-info/WHEEL
dir_handeler-0.0.1.dist-info/top_level.txt
dir_handeler-0.0.1.dist-info/RECORD
