Metadata-Version: 2.1
Name: dir_handeler
Version: 0.0.1
Summary: Handle directory.
Home-page: https://github.com/SanteriHetekivi/dir_handeler
Author: Santeri Hetekivi
Author-email: development@hetekivi.com
License: UNKNOWN
Project-URL: Bug Tracker, https://github.com/SanteriHetekivi/dir_handeler/issues
Platform: UNKNOWN
Classifier: Programming Language :: Python :: 3
Classifier: License :: OSI Approved :: Apache Software License
Classifier: Operating System :: OS Independent
Requires-Python: >=3.10
License-File: LICENSE
